justnotiondb/__init__.py
justnotiondb/notion.py
justnotiondb/processors.py
justnotiondb-0.2.0.dist-info/LICENSE
justnotiondb-0.2.0.dist-info/METADATA
justnotiondb-0.2.0.dist-info/WHEEL
justnotiondb-0.2.0.dist-info/RECORD
