Metadata-Version: 2.1
Name: justnotiondb
Version: 0.2.0
Summary: A minimalistic python package focused solely on extracting databases from Notion
Home-page: https://github.com/matheussrod/justnotiondb
License: MIT
Author: Matheus S. Rodrigues
Author-email: matheus.srodr@gmail.com
Requires-Python: >=3.11,<4.0
Classifier: License :: OSI Approved :: MIT License
Classifier: Programming Language :: Python :: 3
Classifier: Programming Language :: Python :: 3.11
Classifier: Programming Language :: Python :: 3.12
Classifier: Programming Language :: Python :: 3.13
Requires-Dist: requests (>=2.32.3,<3.0.0)
Project-URL: Repository, https://github.com/matheussrod/justnotiondb
